metlinkpid_http.py
metlinkpid_http-1.0.0.dist-info/LICENSE
metlinkpid_http-1.0.0.dist-info/METADATA
metlinkpid_http-1.0.0.dist-info/WHEEL
metlinkpid_http-1.0.0.dist-info/entry_points.txt
metlinkpid_http-1.0.0.dist-info/top_level.txt
metlinkpid_http-1.0.0.dist-info/RECORD
