Metadata-Version: 2.1
Name: metlinkpid-http
Version: 1.0.0
Summary: HTTP server for Metlink PID
Home-page: https://github.com/Lx/python-metlinkpid-http
Author: Alex Peters
License: UNKNOWN
Platform: UNKNOWN
Classifier: Development Status :: 5 - Production/Stable
Classifier: License :: OSI Approved :: MIT License
Classifier: Natural Language :: English
Classifier: Operating System :: OS Independent
Classifier: Programming Language :: Python :: 3.6
Classifier: Programming Language :: Python :: 3.7
Requires-Python: ~=3.6
Requires-Dist: metlinkpid (~=1.0.1)
Requires-Dist: flask (~=1.0.2)
Requires-Dist: envopt (~=0.2.0)
Requires-Dist: waitress (~=1.3.0)
